datasette_profiles_actors_from_ids/__init__.py
datasette_profiles_actors_from_ids-0.1a0.dist-info/licenses/LICENSE
datasette_profiles_actors_from_ids-0.1a0.dist-info/METADATA
datasette_profiles_actors_from_ids-0.1a0.dist-info/WHEEL
datasette_profiles_actors_from_ids-0.1a0.dist-info/entry_points.txt
datasette_profiles_actors_from_ids-0.1a0.dist-info/top_level.txt
datasette_profiles_actors_from_ids-0.1a0.dist-info/RECORD
