Metadata-Version: 2.4
Name: datasette-profiles-actors-from-ids
Version: 0.1a0
Summary: Use datasette-profiles to return actors_from_ids
Author: Simon Willison
License: Apache-2.0
Project-URL: Homepage, https://github.com/datasette/datasette-profiles-actors-from-ids
Project-URL: Changelog, https://github.com/datasette/datasette-profiles-actors-from-ids/releases
Project-URL: Issues, https://github.com/datasette/datasette-profiles-actors-from-ids/issues
Project-URL: CI, https://github.com/datasette/datasette-profiles-actors-from-ids/actions
Classifier: Framework :: Datasette
Classifier: License :: OSI Approved :: Apache Software License
Requires-Python: >=3.9
License-File: LICENSE
Requires-Dist: datasette
Requires-Dist: datasette-profiles>=0.1a3
Provides-Extra: test
Requires-Dist: pytest; extra == "test"
Requires-Dist: pytest-asyncio; extra == "test"
Dynamic: license-file
